{
	"configurations" : 
	[
		{
			"directories" : 
			[
				{
					"build" : ".",
					"jsonFile" : "directory-.-Debug-d0094a50bb2071803777.json",
					"minimumCMakeVersion" : 
					{
						"string" : "3.30"
					},
					"projectIndex" : 0,
					"source" : ".",
					"targetIndexes" : 
					[
						0,
						1,
						2,
						3
					]
				}
			],
			"name" : "Debug",
			"projects" : 
			[
				{
					"directoryIndexes" : 
					[
						0
					],
					"name" : "practice",
					"targetIndexes" : 
					[
						0,
						1,
						2,
						3
					]
				}
			],
			"targets" : 
			[
				{
					"directoryIndex" : 0,
					"id" : "main.cpp::@6890427a1f51a3e7e1df",
					"jsonFile" : "target-main.cpp-Debug-7a3b72120a3da6eed35b.json",
					"name" : "main.cpp",
					"projectIndex" : 0
				},
				{
					"directoryIndex" : 0,
					"id" : "test1.cpp::@6890427a1f51a3e7e1df",
					"jsonFile" : "target-test1.cpp-Debug-249b9c2cd02ea9aed2e8.json",
					"name" : "test1.cpp",
					"projectIndex" : 0
				},
				{
					"directoryIndex" : 0,
					"id" : "test2.cpp::@6890427a1f51a3e7e1df",
					"jsonFile" : "target-test2.cpp-Debug-235c2b91794b7243550b.json",
					"name" : "test2.cpp",
					"projectIndex" : 0
				},
				{
					"directoryIndex" : 0,
					"id" : "test3.cpp::@6890427a1f51a3e7e1df",
					"jsonFile" : "target-test3.cpp-Debug-4486852c82c4f4568e67.json",
					"name" : "test3.cpp",
					"projectIndex" : 0
				}
			]
		}
	],
	"kind" : "codemodel",
	"paths" : 
	{
		"build" : "E:/Code/clion_code/practice/cmake-build-debug",
		"source" : "E:/Code/clion_code/practice"
	},
	"version" : 
	{
		"major" : 2,
		"minor" : 7
	}
}
